hong_beom_do-0.3.0.dist-info/METADATA
hong_beom_do-0.3.0.dist-info/WHEEL
hong_beom_do/__init__.py
hong_beom_do/hero.py
hong_beom_do-0.3.0.dist-info/RECORD
