Metadata-Version: 2.1
Name: hong-beom-do
Version: 0.3.0
Summary: Hong Beom-do was a Korean independence activist who led the Korean Independence Army against the Japanese during the Japanese occupation of Korea.
Author-Email: dmario24 <data.mario24@gmail.com>
License: MIT
Requires-Python: >=3.7
